gryphon_money-1.2.1.dist-info/METADATA
gryphon_money-1.2.1.dist-info/RECORD
gryphon_money-1.2.1.dist-info/WHEEL
gryphon_money-1.2.1.dist-info/top_level.txt
money/__init__.py
money/exceptions.py
money/exchange.py
money/money.py
